fadder.v
module fadder(a,b,c,S,C);
input a,b,c;
output S,C;
assign S=a^b^c;
assign C=a&b|b&c|c&a;
endmodule

fadder_tb.v
module fadder_tb;
reg t_a,t_b,t_c;
wire t_S,t_C;
fadder my_fadder(.a(t_a),.b(t_b),.c(t_c),.S(t_S),.C(t_C));
initial begin $dumpfile("fadder_tb.vcd");$dumpvars(0,fadder_tb);end
initial
begin
	$monitor(t_a,t_b,t_c,t_S,t_C);
	t_a=1'b0;
	t_b=1'b0;
	t_c=1'b0;
	#5
	t_a=1'b0;
	t_b=1'b0;
	t_c=1'b1;
	#5
	t_a=1'b0;
	t_b=1'b1;
	t_c=1'b0;
	#5
	t_a=1'b0;
	t_b=1'b1;
	t_c=1'b1;
	#5
	t_a=1'b1;
	t_b=1'b0;
	t_c=1'b0;
	#5
	t_a=1'b1;
	t_b=1'b0;
	t_c=1'b1;
	#5
	t_a=1'b1;
	t_b=1'b1;
	t_c=1'b0;
	#5
	t_a=1'b1;
	t_b=1'b1;
	t_c=1'b1;
	#5
	t_a=1'b0;
	t_b=1'b0;
	t_c=1'b0;
end
endmodule

fadder_tb.vcd
$date
	Tue Sep  4 09:37:04 2018
$end
$version
	Icarus Verilog
$end
$timescale
	1s
$end
$scope module fadder_tb $end
$var wire 1 ! t_C $end
$var wire 1 " t_S $end
$var reg 1 # t_a $end
$var reg 1 $ t_b $end
$var reg 1 % t_c $end
$scope module my_fadder $end
$var wire 1 ! C $end
$var wire 1 " S $end
$var wire 1 & a $end
$var wire 1 ' b $end
$var wire 1 ( c $end
$upscope $end
$upscope $end
$enddefinitions $end
#0
$dumpvars
0(
0'
0&
0%
0$
0#
0"
0!
$end
#5
1"
1%
1(
#10
0%
0(
1$
1'
#15
1!
0"
1%
1(
#20
0!
1"
0%
0(
0$
0'
1#
1&
#25
1!
0"
1%
1(
#30
0%
0(
1$
1'
#35
1"
1%
1(
#40
0!
0"
0%
0(
0$
0'
0#
0&
